pytools/__init__.py
pytools/bc.py
pytools/build.py
pytools_ca-1.0.0.dist-info/LICENSE.txt
pytools_ca-1.0.0.dist-info/METADATA
pytools_ca-1.0.0.dist-info/WHEEL
pytools_ca-1.0.0.dist-info/top_level.txt
pytools_ca-1.0.0.dist-info/RECORD
