Metadata-Version: 2.1
Name: pytools-ca
Version: 1.0.0
Summary: Just a collection of useful tools to make coding a bit easier.
Home-page: https://cmplxapps.github.io
Author: cmplxapps
Author-email: cmplxapps@gmail.com
License: UNKNOWN
Platform: UNKNOWN
Classifier: Programming Language :: Python :: 3
Classifier: Operating System :: OS Independent
Requires-Python: >=3.6
